CONTRIBUTING.md
MANIFEST.in
README.rst
setup.py
docs/HISTORY.txt
docs/LICENSE.GPL
docs/LICENSE.txt
eea/__init__.py
eea.app.visualization.egg-info/PKG-INFO
eea.app.visualization.egg-info/SOURCES.txt
eea.app.visualization.egg-info/dependency_links.txt
eea.app.visualization.egg-info/entry_points.txt
eea.app.visualization.egg-info/namespace_packages.txt
eea.app.visualization.egg-info/not-zip-safe
eea.app.visualization.egg-info/requires.txt
eea.app.visualization.egg-info/top_level.txt
eea/app/__init__.py
eea/app/visualization/README.txt
eea/app/visualization/__init__.py
eea/app/visualization/common.zcml
eea/app/visualization/config.py
eea/app/visualization/configure.zcml
eea/app/visualization/interfaces.py
eea/app/visualization/meta.zcml
eea/app/visualization/permissions.zcml
eea/app/visualization/plone.zcml
eea/app/visualization/profiles.zcml
eea/app/visualization/version.txt
eea/app/visualization/zope2.zcml
eea/app/visualization/browser/__init__.py
eea/app/visualization/browser/configure.zcml
eea/app/visualization/browser/app/__init__.py
eea/app/visualization/browser/app/depiction.py
eea/app/visualization/browser/app/download.py
eea/app/visualization/browser/app/edit.py
eea/app/visualization/browser/app/view.py
eea/app/visualization/browser/css/bootstrap.css
eea/app/visualization/browser/css/buttons.css
eea/app/visualization/browser/css/common.css
eea/app/visualization/browser/css/edit.css
eea/app/visualization/browser/css/view.css
eea/app/visualization/browser/img/background.png
eea/app/visualization/browser/img/exhibit-icon.png
eea/app/visualization/browser/img/glyphicons-halflings-white.png
eea/app/visualization/browser/img/glyphicons-halflings.png
eea/app/visualization/browser/img/hide.png
eea/app/visualization/browser/img/loading.gif
eea/app/visualization/browser/img/presentation_icon.png
eea/app/visualization/browser/img/show.png
eea/app/visualization/browser/js/common.js
eea/app/visualization/browser/js/edit.js
eea/app/visualization/browser/js/view.js
eea/app/visualization/browser/res/__init__.py
eea/app/visualization/browser/res/configure.zcml
eea/app/visualization/browser/res/css.py
eea/app/visualization/browser/res/interfaces.py
eea/app/visualization/browser/res/javascript.py
eea/app/visualization/browser/res/resources.py
eea/app/visualization/browser/zpt/add-facets.pt
eea/app/visualization/browser/zpt/download-schema.pt
